teach_liuliumcp_mcp_demo/__init__.py
teach_liuliumcp_mcp_demo-0.1.0.dist-info/METADATA
teach_liuliumcp_mcp_demo-0.1.0.dist-info/WHEEL
teach_liuliumcp_mcp_demo-0.1.0.dist-info/entry_points.txt
teach_liuliumcp_mcp_demo-0.1.0.dist-info/RECORD
