Metadata-Version: 2.4
Name: teach-liuliumcp-mcp-demo
Version: 0.1.0
Summary: Add your description here
Author-email: liuliu <1323755910@qq.com>
Requires-Python: >=3.13
Requires-Dist: mcp[cli]>=1.9.4
